fuzzyduration/__init__.py
fuzzyduration-0.2.0.dist-info/WHEEL
fuzzyduration-0.2.0.dist-info/METADATA
fuzzyduration-0.2.0.dist-info/RECORD
